{
    "parent": "overlord:overlord/root",
    "criteria": {
        "has_muscle_skeleton": {
            "conditions": {
                "hasMuscles": true,
                "phase": "BABY"
            },
            "trigger": "overlord:skeleton_grown"
        }
    },
    "display": {
        "announce_to_chat": true,
        "description": {
            "translate": "advancements.overlord.bodybuilder.description"
        },
        "frame": "task",
        "hidden": false,
        "icon": {
            "item": "minecraft:beef"
        },
        "show_toast": true,
        "title": {
            "translate": "advancements.overlord.bodybuilder.title"
        }
    },
    "requirements": [
        [
            "has_muscle_skeleton"
        ]
    ]
}